lib/__init__.py
lib/nikhil.py
Topsis_nikhil_102103482-0.0.2.dist-info/METADATA
Topsis_nikhil_102103482-0.0.2.dist-info/WHEEL
Topsis_nikhil_102103482-0.0.2.dist-info/top_level.txt
Topsis_nikhil_102103482-0.0.2.dist-info/RECORD
